{"chunk_definitions":[{"row":69,"row_count":1,"visible":true,"expansion_state":0,"options":{"engine":"r","label":"setup,","include":false,"message":false,"warning":false,"results":"hide","dev":"png"},"document_id":"A5088FDD","chunk_id":"csetup_chunk","chunk_label":"setup"},{"row":135,"row_count":1,"visible":true,"expansion_state":0,"options":{"engine":"r","echo":false,"warning":false,"label":"unnamed-chunk-9","dev":"png"},"document_id":"A5088FDD","chunk_id":"calm1trrv2bb2","chunk_label":"unnamed-chunk-3"},{"row":143,"row_count":1,"visible":true,"expansion_state":0,"options":{"engine":"r","echo":false,"warning":false,"label":"unnamed-chunk-10","dev":"png"},"document_id":"A5088FDD","chunk_id":"clvzw5vc1mdm0","chunk_label":"unnamed-chunk-4"},{"row":166,"row_count":1,"visible":true,"expansion_state":0,"options":{"engine":"r","warning":false,"label":"unnamed-chunk-14","dev":"png"},"document_id":"A5088FDD","chunk_id":"chkrnm2pi4y7e","chunk_label":"unnamed-chunk-5"},{"row":174,"row_count":1,"visible":true,"expansion_state":0,"options":{"engine":"r","warning":false,"label":"unnamed-chunk-15","dev":"png"},"document_id":"A5088FDD","chunk_id":"ckty9aobfphcr","chunk_label":"unnamed-chunk-6"},{"row":197,"row_count":1,"visible":true,"expansion_state":0,"options":{"engine":"r","warning":false,"label":"unnamed-chunk-16","dev":"png"},"document_id":"A5088FDD","chunk_id":"c9nvumff3b32t","chunk_label":"unnamed-chunk-7"},{"row":205,"row_count":1,"visible":true,"expansion_state":0,"options":{"engine":"r","warning":false,"label":"unnamed-chunk-17","dev":"png"},"document_id":"A5088FDD","chunk_id":"ck2fstz0ldmjq","chunk_label":"unnamed-chunk-8"},{"row":261,"row_count":1,"visible":true,"expansion_state":0,"options":{"engine":"r","warning":false,"label":"unnamed-chunk-30","dev":"png"},"document_id":"A5088FDD","chunk_id":"c5nz5clnskjh3","chunk_label":"unnamed-chunk-11"}],"doc_write_time":1707739347,"chunk_rendered_width":678}